quick_browser/__init__.py
quick_browser/_version.py
quick_browser/cli.py
quick_browser/config.py
quick_browser/download.py
quick_browser/exceptions.py
quick_browser/py.typed
quick_browser/system.py
quick_browser/types.py
quick_browser/chromium/__init__.py
quick_browser/chromium/downloader.py
quick_browser/chromium/extractor.py
quick_browser/chromium/manager.py
quick_browser/chromium/platform.py
quick_browser/chromium/version.py
quick_browser/core/__init__.py
quick_browser/core/browser_utilities.py
quick_browser/core/driver_manager.py
quick_browser/core/element_interactions.py
quick_browser/core/framework.py
quick_browser/core/profile_manager.py
quick_browser/core/troubleshooting.py
quick_browser/core/webdriver_factory.py
quick_browser/utils/__init__.py
quick_browser/utils/cookie_banner_handler.py
quick_browser/utils/cross_platform.py
quick_browser/utils/element_waiter.py
quick_browser/utils/health_checker.py
quick_browser/utils/performance_monitor.py
quick_browser-2.0.0.dist-info/licenses/LICENSE
scripts/build_chromium_dir.py
scripts/cleanup_pipeline.py
scripts/package.py
scripts/refactor_core_module.py
scripts/refactor_utils_module.py
quick_browser-2.0.0.dist-info/METADATA
quick_browser-2.0.0.dist-info/WHEEL
quick_browser-2.0.0.dist-info/entry_points.txt
quick_browser-2.0.0.dist-info/top_level.txt
quick_browser-2.0.0.dist-info/RECORD
