Metadata-Version: 2.4
Name: quick-browser
Version: 2.0.0
Summary: Cross-platform Browser Framework for Web Automation (Windows & Linux)
Author-email: NoirPi <noirpi@noircoding.de>
Maintainer-email: NoirPi <noirpi@noircoding.de>
License-Expression: MIT
Project-URL: Homepage, https://git.noircoding.de/NoirPi/quick-browser
Project-URL: Repository, https://git.noircoding.de/NoirPi/quick-browser.git
Project-URL: Bug Tracker, https://git.noircoding.de/NoirPi/quick-browser/issues
Project-URL: Documentation, https://git.noircoding.de/noirpi/quick-browser/wiki
Keywords: selenium,browser,automation,chromium,webdriver,cross-platform
Classifier: Development Status :: 4 - Beta
Classifier: Intended Audience :: Developers
Classifier: Operating System :: Microsoft :: Windows
Classifier: Operating System :: POSIX :: Linux
Classifier: Programming Language :: Python :: 3
Classifier: Programming Language :: Python :: 3.9
Classifier: Programming Language :: Python :: 3.10
Classifier: Programming Language :: Python :: 3.11
Classifier: Programming Language :: Python :: 3.12
Classifier: Programming Language :: Python :: 3.13
Classifier: Programming Language :: Python :: 3.14
Classifier: Topic :: Software Development :: Libraries :: Python Modules
Classifier: Topic :: Internet :: WWW/HTTP :: Browsers
Classifier: Topic :: Software Development :: Testing
Requires-Python: >=3.8
License-File: LICENSE
Requires-Dist: selenium>=4.15.0
Requires-Dist: webdriver-manager>=4.0.0
Requires-Dist: requests>=2.31.0
Requires-Dist: tqdm>=4.66.0
Requires-Dist: pywin32>=306; sys_platform == "win32"
Provides-Extra: dev
Requires-Dist: pytest>=7.0.0; extra == "dev"
Requires-Dist: ruff; extra == "dev"
Requires-Dist: mypy>=1.0.0; extra == "dev"
Provides-Extra: build
Requires-Dist: nuitka>=1.8.0; extra == "build"
Requires-Dist: colorama>=0.4.6; extra == "build"
Requires-Dist: build>=1.0.0; extra == "build"
Requires-Dist: twine>=4.0.0; extra == "build"
Dynamic: license-file
